.gitignore
.travis.yml
LICENSE
MANIFEST.in
README.md
setup.cfg
setup.py
tests.py
precog/__init__.py
precog/install.py
precog.egg-info/PKG-INFO
precog.egg-info/SOURCES.txt
precog.egg-info/dependency_links.txt
precog.egg-info/entry_points.txt
precog.egg-info/requires.txt
precog.egg-info/top_level.txt