Metadata-Version: 1.0
Name: precog
Version: 0.0.2
Summary: Git-hooks for flake8, isort and eslint
Home-page: https://github.com/isotoma/precog
Author: Isotoma Limited
Author-email: support@isotoma.com
License: Apache Software License
Platform: UNKNOWN
